<?xml version="1.0" encoding="utf-8" ?>
 
 <introContent>
    <extensionContent id="org.eclipse.stem.noteworthy" name="STEM"
        style="css/whatsnew.css" alt-style="css/whatsnew.properties" path="whatsnew/@">
        <group id="content-group" style-id="content-group">
            <link label="STEM"
                url="http://www.eclipse.org/stem"
                id="stem-noteworthy" style-id="content-link">
                <text>STEM Project page</text>    
            </link>        
        </group>           
    </extensionContent>
 </introContent>